<annotation>
    <filename>85.jpg</filename>
    <size>
        <width>104</width>
        <height>33</height>
        <depth>3</depth>
    </size>
    <object>
        <name>A</name>
        <bndbox>
            <xmin>18</xmin>
            <ymin>0</ymin>
            <xmax>30</xmax>
            <ymax>27</ymax>
        </bndbox>
        <name>L</name>
        <bndbox>
            <xmin>36</xmin>
            <ymin>5</ymin>
            <xmax>47</xmax>
            <ymax>27</ymax>
        </bndbox>
        <name>7</name>
        <bndbox>
            <xmin>49</xmin>
            <ymin>6</ymin>
            <xmax>60</xmax>
            <ymax>28</ymax>
        </bndbox>
        <name>7</name>
        <bndbox>
            <xmin>63</xmin>
            <ymin>6</ymin>
            <xmax>74</xmax>
            <ymax>28</ymax>
        </bndbox>
        <name>7</name>
        <bndbox>
            <xmin>76</xmin>
            <ymin>1</ymin>
            <xmax>87</xmax>
            <ymax>28</ymax>
        </bndbox>
        <name>7</name>
        <bndbox>
            <xmin>89</xmin>
            <ymin>6</ymin>
            <xmax>100</xmax>
            <ymax>28</ymax>
        </bndbox>

    </object>
</annotation>
